qweather/MW_client.py
qweather/__init__.py
qweather/broker.py
qweather/client.py
qweather/constants.py
qweather/server.py
QWeather-2.1.1.dist-info/LICENSE.txt
QWeather-2.1.1.dist-info/METADATA
QWeather-2.1.1.dist-info/WHEEL
QWeather-2.1.1.dist-info/top_level.txt
QWeather-2.1.1.dist-info/RECORD
