Metadata-Version: 2.1
Name: QWeather
Version: 2.1.1
Summary: A zeromq based distributed messaging platform
Home-page: https://github.com/Arvad/QWeather
Author: A. Arvad Joergensen
Author-email: Asbjorn.Arvad@nbi.ku.dk
License: MIT
Platform: UNKNOWN
License-File: LICENSE.txt
Requires-Dist: pyzmq (>=17.0.0.b3)
